mvg_api/__init__.py
mvg_api-1.2.7.dist-info/LICENSE
mvg_api-1.2.7.dist-info/METADATA
mvg_api-1.2.7.dist-info/WHEEL
mvg_api-1.2.7.dist-info/top_level.txt
mvg_api-1.2.7.dist-info/RECORD
