Metadata-Version: 2.1
Name: mvg-api
Version: 1.2.7
Summary: Library for fetching departure and route data from the Munich public transport organisation MVG
Home-page: https://github.com/leftshift/python_mvg_api
Author: leftshift
Author-email: leftshiftlp@gmail.com
License: MIT
Platform: UNKNOWN
Classifier: Development Status :: 5 - Production/Stable
Classifier: License :: OSI Approved :: MIT License
Classifier: Intended Audience :: Developers
Classifier: Topic :: Internet :: WWW/HTTP :: Dynamic Content
Classifier: Programming Language :: Python :: 3
Classifier: Programming Language :: Python :: 3.5
Classifier: Programming Language :: Python :: 3.6
Classifier: Programming Language :: Python :: 3.7
Classifier: Programming Language :: Python :: 3.8
